payamresan.py
payamresan-0.1.5.dist-info/METADATA
payamresan-0.1.5.dist-info/WHEEL
payamresan-0.1.5.dist-info/top_level.txt
payamresan-0.1.5.dist-info/RECORD
