Metadata-Version: 2.4
Name: payamresan
Version: 0.1.5
Summary: SMS sending module for payam-resan.com
Author-email: Ali Heydari <imrrobat@gmail.com>
Project-URL: Homepage, https://github.com/imrrobat/payamresan
Project-URL: Payamresan, https://payam-resan.com/
Keywords: sms,payamak,payamresan
Classifier: Programming Language :: Python :: 3
Classifier: License :: OSI Approved :: MIT License
Classifier: Operating System :: OS Independent
Requires-Python: >=3.7
Requires-Dist: requests
